starlette_auth_toolkit/__init__.py
starlette_auth_toolkit/backends.py
starlette_auth_toolkit/cryptography.py
starlette_auth_toolkit/datatypes.py
starlette_auth_toolkit/exceptions.py
starlette_auth_toolkit/base/__init__.py
starlette_auth_toolkit/base/backends.py
starlette_auth_toolkit/contrib/__init__.py
starlette_auth_toolkit/contrib/orm.py
starlette_auth_toolkit-0.5.0.dist-info/LICENSE
starlette_auth_toolkit-0.5.0.dist-info/METADATA
starlette_auth_toolkit-0.5.0.dist-info/WHEEL
starlette_auth_toolkit-0.5.0.dist-info/top_level.txt
starlette_auth_toolkit-0.5.0.dist-info/RECORD
