Metadata-Version: 2.1
Name: starlette-auth-toolkit
Version: 0.5.0
Summary: Authentication backends and helpers for Starlette-based ASGI apps and frameworks
Home-page: https://github.com/florimondmanca/starlette-auth-toolkit.git
Author: Florimond Manca
Author-email: florimond.manca@gmail.com
License: License :: OSI Approved :: MIT License
Platform: UNKNOWN
Classifier: Programming Language :: Python
Classifier: Programming Language :: Python :: 3
Classifier: Programming Language :: Python :: 3 :: Only
Classifier: Programming Language :: Python :: 3.6
Classifier: Programming Language :: Python :: 3.7
Classifier: Operating System :: OS Independent
Requires-Python: >=3.6
Requires-Dist: starlette (>=0.11)
Provides-Extra: dev
Requires-Dist: pytest ; extra == 'dev'
Requires-Dist: pytest-asyncio ; extra == 'dev'
Requires-Dist: requests ; extra == 'dev'
Requires-Dist: uvicorn ; extra == 'dev'
Requires-Dist: argon2-cffi ; extra == 'dev'
Requires-Dist: bcrypt ; extra == 'dev'
Requires-Dist: orm ; extra == 'dev'
Requires-Dist: databases[sqlite] ; extra == 'dev'
Requires-Dist: black ; extra == 'dev'
Requires-Dist: pylint ; extra == 'dev'
Requires-Dist: bumpversion ; extra == 'dev'
Provides-Extra: passwords
Requires-Dist: passlib (<2,>=1.7) ; extra == 'passwords'
